poetic/__init__.py
poetic/__main__.py
poetic/exceptions.py
poetic/gui.py
poetic/predictor.py
poetic/results.py
poetic/util.py
poetic/data/word_dictionary_complete.txt
poetic_py-1.1.0.dist-info/LICENSE.txt
poetic_py-1.1.0.dist-info/METADATA
poetic_py-1.1.0.dist-info/WHEEL
poetic_py-1.1.0.dist-info/top_level.txt
poetic_py-1.1.0.dist-info/RECORD
