Metadata-Version: 2.1
Name: poetic-py
Version: 1.1.0
Summary: A poetry predictor and toolkit.
Home-page: https://github.com/kevin931/poetic
Author: Kevin Wang
Author-email: bridgemarian@gmail.com
License: UNKNOWN
Platform: UNKNOWN
Classifier: License :: OSI Approved :: MIT License
Classifier: Programming Language :: Python :: 3 :: Only
Classifier: Natural Language :: English
Requires-Python: >=3.5, <3.9
Requires-Dist: tensorflow (>=2)
Requires-Dist: gensim
Requires-Dist: nltk
Requires-Dist: numpy
